TelegramBot/TelegramBot.py
TelegramBot/__init__.py
TelegramBot_API-0.0.1.dist-info/METADATA
TelegramBot_API-0.0.1.dist-info/WHEEL
TelegramBot_API-0.0.1.dist-info/top_level.txt
TelegramBot_API-0.0.1.dist-info/RECORD
